{"singlePage": [], "startSite": "", "filingNum": "", "onePageListNum": 15, "commentLabelColor": "#006b75", "yearColorList": ["#bc4c00", "#0969da", "#1f883d", "#A333D0"], "i18n": "CN", "themeMode": "manual", "dayTheme": "light", "nightTheme": "dark", "urlMode": "pinyin", "script": "", "style": "", "head": "", "indexScript": "", "indexStyle": "", "bottomText": "", "showPostSource": 1, "iconList": {}, "UTC": 8, "rssSplit": "sentence", "exlink": {}, "needComment": 1, "allHead": "", "title": "WangHaoLin827\u7684\u535a\u5ba2Blog", "subTitle": "\u90ae\u7bb1\uff1awanghaolin827@outlook.com", "avatarUrl": "https://avatars.githubusercontent.com/u/180376951?v=4&size=64", "GMEEK_VERSION": "last", "postListJson": {"P1": {"htmlDir": "docs/post/ce-shi.html", "labels": ["documentation"], "postTitle": "\u6d4b\u8bd5", "postUrl": "post/ce-shi.html", "postSourceUrl": "https://github.com/WangHaoLin827/WangHaoLin827.github.io/issues/1", "commentNum": 1, "wordCount": 4, "description": "\u6d4b\u8bd5\u6210\u529f\u3002", "top": 0, "createdAt": 1741448785, "style": "", "script": "", "head": "", "ogImage": "https://avatars.githubusercontent.com/u/180376951?v=4&size=64", "createdDate": "2025-03-08", "dateLabelColor": "#0969da"}, "P4": {"htmlDir": "docs/post/\u3010-sheng-cun-zhi-jing-\u3011Minecraft 1.21.4-chun-jing-sheng-cun-fu-wu-qi-jie-shao.html", "labels": ["documentation"], "postTitle": "\u3010\u751f\u5b58\u4e4b\u5883\u3011Minecraft 1.21.4\u7eaf\u51c0\u751f\u5b58\u670d\u52a1\u5668\u4ecb\u7ecd", "postUrl": "post/%E3%80%90-sheng-cun-zhi-jing-%E3%80%91Minecraft%201.21.4-chun-jing-sheng-cun-fu-wu-qi-jie-shao.html", "postSourceUrl": "https://github.com/WangHaoLin827/WangHaoLin827.github.io/issues/4", "commentNum": 0, "wordCount": 808, "description": "\u4eb2\u7231\u7684\u5192\u9669\u8005\uff1a\n\n\u6b22\u8fce\u6765\u5230\u3010\u751f\u5b58\u4e4b\u5883\u3011\u2014\u2014\u4e00\u4e2a\u4e13\u6ce8\u4e8e\u539f\u7248\u751f\u5b58\u4f53\u9a8c\u7684\u65b0\u751f\u670d\u52a1\u5668\uff01\u6211\u4eec\u4e8e2025\u5e743\u67083\u65e5\u521a\u521a\u542f\u822a\uff08\u5f00\u670d\u65f6\u95f4\u53ef\u8865\u5145\uff09\uff0c\u81f4\u529b\u4e8e\u4e3a\u73a9\u5bb6\u6253\u9020\u81ea\u7531\u5f00\u653e\u7684\u6c99\u76d2\u4e16\u754c\u3002", "top": 0, "createdAt": 1741507479, "style": "", "script": "", "head": "", "ogImage": "https://avatars.githubusercontent.com/u/180376951?v=4&size=64", "createdDate": "2025-03-09", "dateLabelColor": "#0969da"}}, "singeListJson": {}, "labelColorDict": {"bug": "#d73a4a", "documentation": "#0075ca", "duplicate": "#cfd3d7", "enhancement": "#a2eeef", "good first issue": "#7057ff", "help wanted": "#008672", "invalid": "#e4e669", "question": "#d876e3", "wontfix": "#ffffff"}, "displayTitle": "WangHaoLin827\u7684\u535a\u5ba2Blog", "faviconUrl": "https://avatars.githubusercontent.com/u/180376951?v=4&size=64", "ogImage": "https://avatars.githubusercontent.com/u/180376951?v=4&size=64", "primerCSS": "<link href='https://mirrors.sustech.edu.cn/cdnjs/ajax/libs/Primer/21.0.7/primer.css' rel='stylesheet' />", "homeUrl": "https://WangHaoLin827.github.io", "prevUrl": "disabled", "nextUrl": "disabled"}